{
"autoplayBgm":false,"autoplayBgs":false,"battleback1Name":"battleback_indoors","battleback2Name":"","bgm":{"name":"Farmstead","pan":0,"pitch":100,"volume":90},"bgs":{"name":"","pan":0,"pitch":100,"volume":90},"disableDashing":false,"displayName":"","encounterList":[],"encounterStep":30,"height":13,"note":"","parallaxLoopX":false,"parallaxLoopY":false,"parallaxName":"Day","parallaxShow":false,"parallaxSx":0,"parallaxSy":0,"scrollType":0,"specifyBattleback":true,"tilesetId":1,"width":17,
"data":[0,0,0,0,0,0,0,0,0,0,0,0,0,0,0,0,0,0,0,0,0,0,0,0,0,0,0,0,0,0,0,0,0,0,0,0,0,0,0,0,0,2481,2482,0,0,0,0,0,0,0,0,0,0,0,0,0,2481,2480,2480,2480,2480,2482,0,0,0,0,0,0,0,0,0,0,0,2481,2480,2480,2480,2480,2480,2480,2482,0,0,0,0,0,0,0,0,2481,2480,2480,2480,2480,2480,2480,2482,0,0,0,0,0,0,0,0,1536,2481,2480,2480,2480,2480,2480,2480,2482,1536,1536,1536,0,0,0,0,0,1536,1544,1544,1544,1544,1544,1544,1544,1544,1536,1536,0,0,0,1536,1536,1536,1536,0,1544,1544,1544,1544,1544,1544,1544,1536,1536,1536,1536,1536,0,0,0,0,0,0,0,0,0,0,0,0,0,0,0,0,0,1544,1544,1544,1544,1544,1544,1544,1544,1544,1544,1544,1544,1544,1544,1544,1544,1544,1544,1544,1544,1544,1544,1544,1544,1544,1544,1544,1544,1544,1544,1544,1544,1544,1544,1544,1544,1544,1544,1544,1544,1544,1544,1544,1544,1544,1544,1544,1544,1544,1544,1544,0,0,0,0,0,0,0,0,0,0,0,0,0,0,0,0,0,0,0,0,0,0,0,0,0,0,0,0,0,0,0,0,0,0,0,0,0,0,0,0,0,0,0,0,0,0,0,0,0,0,0,0,0,0,0,0,0,0,0,0,0,0,0,0,0,0,0,0,0,0,0,0,0,0,0,0,0,0,0,0,0,0,0,0,0,0,0,0,0,0,0,0,0,0,0,0,0,0,0,0,0,0,0,0,0,0,0,0,0,0,0,0,0,0,0,0,0,0,0,0,0,0,0,0,0,0,0,0,0,0,0,0,0,0,0,0,0,0,0,0,0,0,0,0,0,0,0,0,0,0,0,0,0,0,0,0,0,0,0,0,0,0,0,0,0,0,0,0,0,0,0,0,0,0,0,0,0,0,0,0,0,0,0,0,0,0,0,0,0,0,0,0,0,0,0,0,0,0,0,0,0,0,0,0,0,0,0,0,0,0,0,0,0,0,0,0,0,0,0,0,0,0,0,0,0,0,0,0,0,0,0,0,0,0,0,0,0,0,0,0,0,0,0,0,0,0,0,0,0,0,0,0,0,0,0,0,0,0,0,0,0,0,0,0,0,0,0,0,0,0,0,0,0,0,0,0,0,0,0,0,0,0,0,0,0,0,0,0,0,0,0,0,0,0,0,0,0,0,0,0,0,0,0,0,0,0,0,0,0,0,0,0,0,0,0,0,0,0,0,0,0,0,0,0,0,0,0,0,0,0,0,0,0,0,0,0,0,0,0,0,0,0,0,0,81,0,0,0,0,0,0,0,0,0,0,0,0,0,0,0,0,0,0,0,0,0,0,0,80,0,0,0,0,0,76,76,76,76,76,76,76,76,76,76,76,76,205,205,76,76,76,0,0,0,0,0,0,0,0,0,0,0,0,0,0,0,0,0,0,0,0,0,0,0,0,0,0,0,0,0,0,0,0,0,0,0,0,0,0,0,0,0,0,0,0,0,0,0,0,0,0,0,0,0,0,0,0,0,0,0,0,0,0,0,0,0,0,0,0,0,0,0,0,0,0,0,0,0,0,0,0,0,0,0,0,0,0,0,0,0,0,0,0,0,0,0,0,0,0,0,0,0,0,0,0,0,0,0,0,0,0,0,0,0,0,0,0,0,0,0,0,0,0,0,0,0,0,0,0,0,0,0,0,0,0,0,0,0,0,0,0,0,214,24,24,24,24,215,0,0,0,0,0,0,0,0,0,0,214,24,24,24,24,24,24,215,0,0,0,0,0,0,0,0,214,24,0,0,0,0,0,0,80,215,0,0,0,0,0,0,0,0,8,0,0,238,241,245,234,57,0,0,0,0,0,52,52,52,52,205,205,205,205,205,205,205,205,52,52,52,52,52,0,0,0,0,0,0,0,0,0,0,0,0,0,0,0,0,0,0,0,0,0,0,0,0,0,0,0,0,0,0,0,0,0,0,0,0,0,0,0,0,0,0,0,0,0,0,0,0,0,0,0,0,0,0,0,0,0,0,0,0,0,0,0,0,0,0,0,0,0,0,0,0,0,0,0,0,0,0,0,0,0,0,0,0,0,0,0,0,0,0,0,0,0,0,0,0,0,0,0,0,0,0,0,0,0,0,0,0,0,0,0,0,0,0,0,0,0,0,0,0,0,0,0,0,0,0,0,0,0,0,0,0,0,0,0,0,0,0,0,0,0,0,0,0,0,0,0,0,0,0,0,0,0,0,0,0,0,0,0,0,0,0,0,0,0,0,0,0,0,0,0,0,0,0,0,0,0,0,0,0,0,0,0,0,0,0,0,0,0,0,0,0,0,0,0,0,0,0,0,0,0,0,0,0,0,0,0,0,0,0,0,0,0,0,0,0,0,0,0,0,0,0,0,0,0,0,0,0,0,0,0,0,0,0,0,0,0,0,0,0,0,0,0,0,0,0,0,0,0,0,0,0,0,0,0,0,0,0,0,0,0,0,0,0,0,0,0,0,0,0,0,0,1,1,1,1,1,1,1,1,1,1,1,1,1,1,1,1,1,1,1,1,1,1,1,1,1,1,1,1,1,1,1,1,1,1,1,1,1,1,1,1,1,1,1,1,1,1,1,1,1,1,1,1,1,1,1,1,1,1,1,1,1,1,1,1,1,1,1,1,1,1,1,1,1,1,1,1,1,1,1,1,1,1,1,1,1,1,1,1,1,1,1,1,1,1,1,1,1,1,1,1,1,1,1,1,1,1,1,1,1,1,1,1,1,1,1,1,1,1,1,1,1,1,1,1,1,1,1,1,1,1,1,1,1,1,1,1,0,0,0,0,0,0,0,0,0,0,0,0,1,1,1,1,1,1,1,1,1,1,1,1,1,1,1,1,1,1,1,1,1,1,1,1,1,1,1,1,1,1,1,1,1,1,1,1,1,1,1,1,1,1,1,1,1,1,1,1,1,1,1,1,1,1,1,1,1,1,1,1,1,1,1,1,1,1,1,1,1,1,1,1,1],
"events":[
null,
{"id":1,"name":"EV001","note":"","pages":[{"conditions":{"actorId":1,"actorValid":false,"itemId":1,"itemValid":false,"selfSwitchCh":"A","selfSwitchValid":false,"switch1Id":1,"switch1Valid":false,"switch2Id":1,"switch2Valid":false,"variableId":1,"variableValid":false,"variableValue":0},"directionFix":false,"image":{"tileId":0,"characterName":"!$doorSideways [2 2 2 2]","direction":2,"pattern":0,"characterIndex":0},"list":[{"code":355,"indent":0,"parameters":["Interact.interact(\"Door\", \"FacesObj1_1\", \"It's Locked.\");"]},{"code":111,"indent":0,"parameters":[12,"$gameVariables.value(1).toUpperCase() == \"KNOCK\""]},{"code":101,"indent":1,"parameters":["FacesObj1",0,0,2]},{"code":401,"indent":1,"parameters":["Nobody answers."]},{"code":0,"indent":1,"parameters":[]},{"code":412,"indent":0,"parameters":[]},{"code":111,"indent":0,"parameters":[12,"$gameVariables.value(1).toUpperCase() == \"UNLOCK\""]},{"code":111,"indent":1,"parameters":[8,21]},{"code":126,"indent":2,"parameters":[21,1,0,1]},{"code":123,"indent":2,"parameters":["A",0]},{"code":0,"indent":2,"parameters":[]},{"code":411,"indent":1,"parameters":[]},{"code":101,"indent":2,"parameters":["FacesObj1",0,0,2]},{"code":401,"indent":2,"parameters":["You don't have the required lockpick."]},{"code":0,"indent":2,"parameters":[]},{"code":412,"indent":1,"parameters":[]},{"code":0,"indent":1,"parameters":[]},{"code":412,"indent":0,"parameters":[]},{"code":111,"indent":0,"parameters":[12,"$gameVariables.value(1).toUpperCase() == \"LOOK\""]},{"code":101,"indent":1,"parameters":["FacesObj1",0,0,2]},{"code":401,"indent":1,"parameters":["The door seems to have an intricate lock."]},{"code":0,"indent":1,"parameters":[]},{"code":412,"indent":0,"parameters":[]},{"code":0,"indent":0,"parameters":[]}],"moveFrequency":3,"moveRoute":{"list":[{"code":0,"parameters":[]}],"repeat":true,"skippable":false,"wait":false},"moveSpeed":3,"moveType":0,"priorityType":1,"stepAnime":false,"through":false,"trigger":0,"walkAnime":true},{"conditions":{"actorId":1,"actorValid":false,"itemId":1,"itemValid":false,"selfSwitchCh":"A","selfSwitchValid":true,"switch1Id":1,"switch1Valid":false,"switch2Id":1,"switch2Valid":false,"variableId":1,"variableValid":false,"variableValue":0},"directionFix":false,"image":{"characterIndex":0,"characterName":"","direction":2,"pattern":0,"tileId":0},"list":[{"code":0,"indent":0,"parameters":[]}],"moveFrequency":3,"moveRoute":{"list":[{"code":0,"parameters":[]}],"repeat":true,"skippable":false,"wait":false},"moveSpeed":3,"moveType":0,"priorityType":0,"stepAnime":false,"through":false,"trigger":0,"walkAnime":true}],"x":4,"y":8},
{"id":2,"name":"EV002","note":"","pages":[{"conditions":{"actorId":1,"actorValid":false,"itemId":1,"itemValid":false,"selfSwitchCh":"A","selfSwitchValid":false,"switch1Id":1,"switch1Valid":false,"switch2Id":1,"switch2Valid":false,"variableId":1,"variableValid":false,"variableValue":0},"directionFix":false,"image":{"characterIndex":0,"characterName":"","direction":2,"pattern":0,"tileId":0},"list":[{"code":356,"indent":0,"parameters":["layer refresh"]},{"code":356,"indent":0,"parameters":["LAYER 2 32 fieldsback 0 0 255 -3 0 0 0"]},{"code":356,"indent":0,"parameters":["LAYER 2 33 fields2 0 0 255 -2 -14 0 0"]},{"code":356,"indent":0,"parameters":["LAYER 2 34 fields1 0 0 255 -1 4 0 0"]},{"code":201,"indent":0,"parameters":[0,2,28,8,0,0]},{"code":111,"indent":0,"parameters":[0,227,0]},{"code":241,"indent":1,"parameters":[{"name":"Farmstead","volume":90,"pitch":100,"pan":0}]},{"code":0,"indent":1,"parameters":[]},{"code":411,"indent":0,"parameters":[]},{"code":111,"indent":1,"parameters":[0,11,0]},{"code":241,"indent":2,"parameters":[{"name":"FarmsteadCreepy","volume":90,"pitch":100,"pan":0}]},{"code":0,"indent":2,"parameters":[]},{"code":411,"indent":1,"parameters":[]},{"code":241,"indent":2,"parameters":[{"name":"Farmstead","volume":90,"pitch":100,"pan":0}]},{"code":0,"indent":2,"parameters":[]},{"code":412,"indent":1,"parameters":[]},{"code":0,"indent":1,"parameters":[]},{"code":412,"indent":0,"parameters":[]},{"code":0,"indent":0,"parameters":[]}],"moveFrequency":3,"moveRoute":{"list":[{"code":0,"parameters":[]}],"repeat":true,"skippable":false,"wait":false},"moveSpeed":3,"moveType":0,"priorityType":0,"stepAnime":false,"through":false,"trigger":1,"walkAnime":true}],"x":0,"y":8},
{"id":3,"name":"EV003","note":"","pages":[{"conditions":{"actorId":1,"actorValid":false,"itemId":1,"itemValid":false,"selfSwitchCh":"A","selfSwitchValid":false,"switch1Id":1,"switch1Valid":false,"switch2Id":1,"switch2Valid":false,"variableId":1,"variableValid":false,"variableValue":0},"directionFix":false,"image":{"characterIndex":0,"characterName":"","direction":2,"pattern":0,"tileId":0},"list":[{"code":101,"indent":0,"parameters":["",0,0,2]},{"code":401,"indent":0,"parameters":["You find Antibody Armor."]},{"code":128,"indent":0,"parameters":[19,0,0,1,false]},{"code":123,"indent":0,"parameters":["A",0]},{"code":0,"indent":0,"parameters":[]}],"moveFrequency":3,"moveRoute":{"list":[{"code":0,"parameters":[]}],"repeat":true,"skippable":false,"wait":false},"moveSpeed":3,"moveType":0,"priorityType":0,"stepAnime":false,"through":false,"trigger":0,"walkAnime":true},{"conditions":{"actorId":1,"actorValid":false,"itemId":1,"itemValid":false,"selfSwitchCh":"A","selfSwitchValid":true,"switch1Id":46,"switch1Valid":false,"switch2Id":1,"switch2Valid":false,"variableId":1,"variableValid":false,"variableValue":0},"directionFix":false,"image":{"characterIndex":0,"characterName":"","direction":2,"pattern":0,"tileId":0},"list":[{"code":101,"indent":0,"parameters":["",0,0,2]},{"code":401,"indent":0,"parameters":["It's empty."]},{"code":0,"indent":0,"parameters":[]}],"moveFrequency":3,"moveRoute":{"list":[{"code":0,"parameters":[]}],"repeat":true,"skippable":false,"wait":false},"moveSpeed":3,"moveType":0,"priorityType":0,"stepAnime":false,"through":false,"trigger":0,"walkAnime":true}],"x":9,"y":8},
{"id":4,"name":"EV004","note":"","pages":[{"conditions":{"actorId":1,"actorValid":false,"itemId":1,"itemValid":false,"selfSwitchCh":"A","selfSwitchValid":false,"switch1Id":1,"switch1Valid":false,"switch2Id":1,"switch2Valid":false,"variableId":1,"variableValid":false,"variableValue":0},"directionFix":false,"image":{"characterIndex":0,"characterName":"","direction":2,"pattern":0,"tileId":0},"list":[{"code":101,"indent":0,"parameters":["",0,0,2]},{"code":401,"indent":0,"parameters":["You rest on the bed."]},{"code":249,"indent":0,"parameters":[{"name":"Inn","volume":90,"pitch":100,"pan":0}]},{"code":223,"indent":0,"parameters":[[-255,-255,-255,0],150,true]},{"code":314,"indent":0,"parameters":[0,0]},{"code":230,"indent":0,"parameters":[100]},{"code":223,"indent":0,"parameters":[[0,0,0,0],150,true]},{"code":101,"indent":0,"parameters":["",0,0,2]},{"code":401,"indent":0,"parameters":["You've recovered."]},{"code":0,"indent":0,"parameters":[]}],"moveFrequency":3,"moveRoute":{"list":[{"code":0,"parameters":[]}],"repeat":true,"skippable":false,"wait":false},"moveSpeed":3,"moveType":0,"priorityType":0,"stepAnime":false,"through":false,"trigger":0,"walkAnime":true}],"x":10,"y":8},
{"id":5,"name":"EV005","note":"","pages":[{"conditions":{"actorId":1,"actorValid":false,"itemId":1,"itemValid":false,"selfSwitchCh":"A","selfSwitchValid":false,"switch1Id":405,"switch1Valid":true,"switch2Id":1,"switch2Valid":false,"variableId":1,"variableValid":false,"variableValue":0},"directionFix":false,"image":{"tileId":243,"characterName":"","characterIndex":0,"direction":2,"pattern":0},"list":[{"code":231,"indent":0,"parameters":[1,"lockpick1frame",1,0,400,200,100,100,255,0]},{"code":231,"indent":0,"parameters":[2,"lockpick1outerrotate90",1,0,400,200,100,100,255,0]},{"code":122,"indent":0,"parameters":[107,107,0,0,2]},{"code":231,"indent":0,"parameters":[3,"lockpick1middlerotate45",1,0,400,200,100,100,255,0]},{"code":122,"indent":0,"parameters":[108,108,0,0,1]},{"code":231,"indent":0,"parameters":[4,"lockpick1innerrotate270",1,0,400,200,100,100,255,0]},{"code":122,"indent":0,"parameters":[109,109,0,0,6]},{"code":122,"indent":0,"parameters":[110,110,0,0,0]},{"code":201,"indent":0,"parameters":[0,217,8,8,0,0]},{"code":135,"indent":0,"parameters":[0]},{"code":230,"indent":0,"parameters":[40]},{"code":231,"indent":0,"parameters":[5,"lockpickoutermask",1,0,400,200,100,100,255,0]},{"code":0,"indent":0,"parameters":[]}],"moveFrequency":3,"moveRoute":{"list":[{"code":0,"parameters":[]}],"repeat":true,"skippable":false,"wait":false},"moveSpeed":3,"moveType":0,"priorityType":0,"stepAnime":false,"through":false,"trigger":0,"walkAnime":true},{"conditions":{"actorId":1,"actorValid":false,"itemId":1,"itemValid":false,"selfSwitchCh":"A","selfSwitchValid":false,"switch1Id":405,"switch1Valid":true,"switch2Id":423,"switch2Valid":true,"variableId":1,"variableValid":false,"variableValue":0},"directionFix":false,"image":{"tileId":243,"characterName":"","characterIndex":0,"direction":2,"pattern":0},"list":[{"code":101,"indent":0,"parameters":["",0,0,2]},{"code":401,"indent":0,"parameters":["You find a gold watch."]},{"code":126,"indent":0,"parameters":[95,0,0,1]},{"code":356,"indent":0,"parameters":["Quest 22 hide Objective 1"]},{"code":356,"indent":0,"parameters":["GabText A crusade has been updated."]},{"code":356,"indent":0,"parameters":["ShowGab"]},{"code":213,"indent":0,"parameters":[-1,13,true]},{"code":123,"indent":0,"parameters":["A",0]},{"code":0,"indent":0,"parameters":[]}],"moveFrequency":3,"moveRoute":{"list":[{"code":0,"parameters":[]}],"repeat":true,"skippable":false,"wait":false},"moveSpeed":3,"moveType":0,"priorityType":0,"stepAnime":false,"through":false,"trigger":0,"walkAnime":true},{"conditions":{"actorId":1,"actorValid":false,"itemId":1,"itemValid":false,"selfSwitchCh":"A","selfSwitchValid":false,"switch1Id":405,"switch1Valid":true,"switch2Id":424,"switch2Valid":true,"variableId":1,"variableValid":false,"variableValue":0},"directionFix":false,"image":{"tileId":244,"characterName":"","characterIndex":0,"direction":2,"pattern":0},"list":[{"code":101,"indent":0,"parameters":["",0,0,2]},{"code":401,"indent":0,"parameters":["It's empty."]},{"code":0,"indent":0,"parameters":[]}],"moveFrequency":3,"moveRoute":{"list":[{"code":0,"parameters":[]}],"repeat":true,"skippable":false,"wait":false},"moveSpeed":3,"moveType":0,"priorityType":0,"stepAnime":false,"through":false,"trigger":0,"walkAnime":true}],"x":11,"y":8},
null
]
}